Web_page_Screenshot_Segmentation/__init__.py
Web_page_Screenshot_Segmentation/blank_spliter.py
Web_page_Screenshot_Segmentation/color_spliter.py
Web_page_Screenshot_Segmentation/drawer.py
Web_page_Screenshot_Segmentation/master.py
Web_page_Screenshot_Segmentation/spliter.py
Web_page_Screenshot_Segmentation-1.0.4.dist-info/METADATA
Web_page_Screenshot_Segmentation-1.0.4.dist-info/WHEEL
Web_page_Screenshot_Segmentation-1.0.4.dist-info/top_level.txt
Web_page_Screenshot_Segmentation-1.0.4.dist-info/RECORD
