Metadata-Version: 2.1
Name: Web_page_Screenshot_Segmentation
Version: 1.0.4
Summary: Divide long web page screenshots into blocks to input models with shorter contexts. 将长网页截图进行区块分割，用于输入上下文较短的模型
Author-email: Tim Saijun <code@zair.top>
Project-URL: Homepage, https://github.com/Tim-Saijun/Web_page_Screenshot_Segmentation
Project-URL: Documentation, https://tim-saijun.github.io/Web_page_Screenshot_Segmentation/
Keywords: opencv,website,image segementation,screenshot,gpt
Classifier: Programming Language :: Python :: 3
Classifier: License :: OSI Approved :: MIT License
Classifier: Operating System :: OS Independent
Requires-Python: >=3.9
Requires-Dist: opencv-python
Requires-Dist: numpy
